<?xml version="1.0" encoding="UTF-8"?>
<site>
   <category-def name="org.jactr.eclipse.category" label="jACT-R Eclipse">
      <description>
         jACT-R Eclipse features
      </description>
   </category-def>
   <feature id="org.jactr.eclipse.feature">
      <category name="org.jactr.eclipse.category"/>
   </feature>
   <feature id="org.jactr.eclipse.feature.source">
      <category name="org.jactr.eclipse.category"/>
   </feature>
   <feature id="org.jactr.eclipse.tools.feature">
      <category name="org.jactr.eclipse.category"/>
   </feature>
   <feature id="org.jactr.eclipse.tools.feature.source">
      <category name="org.jactr.eclipse.category"/>
   </feature>
   <category-def name="org.jactr.eclipse.dependencies.category" label="Dependencies of jACT-R Eclipse">
      <description>
         Third-party features required by jACT-R Eclipse
      </description>
   </category-def>
   <feature id="org.jactr.eclipse.bridge.jactr.core.feature">
      <category name="org.jactr.eclipse.category"/>
   </feature>
   <feature id="org.jactr.eclipse.bridge.jactr.core.feature.source">
      <category name="org.jactr.eclipse.category"/>
   </feature>
   <feature id="org.jactr.eclipse.bridge.jactr.io.feature">
      <category name="org.jactr.eclipse.category"/>
   </feature>
   <feature id="org.jactr.eclipse.bridge.jactr.io.feature.source">
      <category name="org.jactr.eclipse.category"/>
   </feature>
   <feature id="org.jactr.eclipse.bridge.jactr.modules.feature">
      <category name="org.jactr.eclipse.category"/>
   </feature>
   <feature id="org.jactr.eclipse.bridge.jactr.modules.feature.source">
      <category name="org.jactr.eclipse.category"/>
   </feature>
   <feature id="org.jactr.eclipse.bridge.jactr.tools.feature">
      <category name="org.jactr.eclipse.category"/>
   </feature>
   <feature id="org.jactr.eclipse.bridge.jactr.tools.feature.source">
      <category name="org.jactr.eclipse.category"/>
   </feature>
    <!-- Note that the repository references need to be kept in sync with the URLs provided in the parent POM -->
	<repository-reference location="http://monochromata.de/eclipse/sites/org.commonreality" enabled="true" />
	<repository-reference location="http://monochromata.de/eclipse/sites/org.jactr" enabled="true" />
	<repository-reference location="http://download.eclipse.org/technology/nebula/snapshot" enabled="true" />
</site>
